rapid_clay_formations_fab/__init__.py
rapid_clay_formations_fab/_cmd_entrypoint.py
rapid_clay_formations_fab/_version.py
rapid_clay_formations_fab/docker.py
rapid_clay_formations_fab/utils.py
rapid_clay_formations_fab/_compose_files/abb-driver/docker-compose.yml
rapid_clay_formations_fab/_compose_files/abb-driver/real.env
rapid_clay_formations_fab/_compose_files/abb-planner/docker-compose.moveit-setup.yml
rapid_clay_formations_fab/_compose_files/abb-planner/docker-compose.novnc.yml
rapid_clay_formations_fab/_compose_files/abb-planner/docker-compose.yml
rapid_clay_formations_fab/fab_data/__init__.py
rapid_clay_formations_fab/fab_data/config_default.yaml
rapid_clay_formations_fab/fab_data/csv_report.py
rapid_clay_formations_fab/fab_data/fab_conf.py
rapid_clay_formations_fab/fab_data/fabrication_element.py
rapid_clay_formations_fab/fab_data/tools.py
rapid_clay_formations_fab/rhino/__init__.py
rapid_clay_formations_fab/rhino/compas_to_rhino.py
rapid_clay_formations_fab/rhino/install.py
rapid_clay_formations_fab/rhino/rhino_to_compas.py
rapid_clay_formations_fab/robots/__init__.py
rapid_clay_formations_fab/robots/abb_rapid_tooldata.py
rapid_clay_formations_fab/robots/abb_rcf_client.py
rapid_clay_formations_fab/robots/abb_standalone_move_to_frame.py
rapid_clay_formations_fab/robots/compas_rrc_docker_setup.py
rapid_clay_formations_fab/robots/custom_compas_rrc_instructions.py
rapid_clay_formations_fab/robots/pick_station.py
rapid_clay_formations_fab/robots/trajectories.py
rapid_clay_formations_fab/robots/_scripts/__init__.py
rapid_clay_formations_fab/robots/_scripts/common.py
rapid_clay_formations_fab/robots/_scripts/fabrication.py
rapid_clay_formations_fab/robots/_scripts/go_to_joint_pos.py
rapid_clay_formations_fab/robots/_scripts/record_poses.py
rapid_clay_formations_fab/robots/_scripts/test_speeds.py
rapid_clay_formations_fab/robots/_scripts/test_speeds_wo_pick.py
rapid_clay_formations_fab-0.7.1.dist-info/AUTHORS.md
rapid_clay_formations_fab-0.7.1.dist-info/LICENSE
rapid_clay_formations_fab-0.7.1.dist-info/METADATA
rapid_clay_formations_fab-0.7.1.dist-info/WHEEL
rapid_clay_formations_fab-0.7.1.dist-info/entry_points.txt
rapid_clay_formations_fab-0.7.1.dist-info/top_level.txt
rapid_clay_formations_fab-0.7.1.dist-info/RECORD
